recoder/__init__.py
recoder/data.py
recoder/embedding.py
recoder/losses.py
recoder/metrics.py
recoder/model.py
recoder/nn.py
recoder/recommender.py
recoder/utils.py
recsys_recoder-0.4.0.dist-info/LICENSE
recsys_recoder-0.4.0.dist-info/METADATA
recsys_recoder-0.4.0.dist-info/WHEEL
recsys_recoder-0.4.0.dist-info/top_level.txt
recsys_recoder-0.4.0.dist-info/RECORD
