Metadata-Version: 2.1
Name: recsys-recoder
Version: 0.4.0
Summary: UNKNOWN
Home-page: https://github.com/amoussawi/recoder
Author: Abdallah Moussawi
Author-email: abdallah.moussawi@gmail.com
License: MIT
Platform: UNKNOWN
Requires-Dist: annoy (==1.17.0)
Requires-Dist: glog (==0.3.1)
Requires-Dist: numpy (==1.19.5)
Requires-Dist: scipy (==1.6.2)
Requires-Dist: torch (==1.8.1)
Requires-Dist: tqdm (==4.59.0)
